starlette/__init__.py
starlette/_exception_handler.py
starlette/_utils.py
starlette/applications.py
starlette/authentication.py
starlette/background.py
starlette/concurrency.py
starlette/config.py
starlette/convertors.py
starlette/datastructures.py
starlette/endpoints.py
starlette/exceptions.py
starlette/formparsers.py
starlette/py.typed
starlette/requests.py
starlette/responses.py
starlette/routing.py
starlette/schemas.py
starlette/staticfiles.py
starlette/status.py
starlette/templating.py
starlette/testclient.py
starlette/types.py
starlette/websockets.py
starlette/middleware/__init__.py
starlette/middleware/authentication.py
starlette/middleware/base.py
starlette/middleware/cors.py
starlette/middleware/errors.py
starlette/middleware/exceptions.py
starlette/middleware/gzip.py
starlette/middleware/httpsredirect.py
starlette/middleware/sessions.py
starlette/middleware/trustedhost.py
starlette/middleware/wsgi.py
starlette-0.52.0.dist-info/METADATA
starlette-0.52.0.dist-info/WHEEL
starlette-0.52.0.dist-info/licenses/LICENSE.md
starlette-0.52.0.dist-info/RECORD
